{
  "_class": "text",
  "attributedString": {
    "_class": "attributedString",
    "attributes": [
      {
        "_class": "stringAttribute",
        "attributes": {
          "MSAttributedStringColorAttribute": {
            "_class": "color",
            "alpha": 1,
            "blue": 0,
            "green": 0,
            "red": 0
          },
          "MSAttributedStringFontAttribute": {
            "_class": "fontDescriptor",
            "attributes": {
              "name": "SFProText-Heavy",
              "size": 24
            }
          },
          "MSAttributedStringTextTransformAttribute": 1,
          "kerning": -1,
          "paragraphStyle": {
            "_class": "paragraphStyle",
            "alignment": 0,
            "maximumLineHeight": 24,
            "minimumLineHeight": 24,
            "paragraphSpacing": 4
          },
          "textStyleVerticalAlignmentKey": 0
        },
        "length": 13,
        "location": 0
      }
    ],
    "string": "Subscriptions"
  },
  "automaticallyDrawOnUnderlyingPath": false,
  "booleanOperation": -1,
  "clippingMaskMode": 0,
  "do_objectID": "D5204D51-FC5C-4709-BCF9-86F091098A30",
  "dontSynchroniseWithSymbol": false,
  "exportOptions": {
    "_class": "exportOptions",
    "do_objectID": "1F90FBF9-1BCC-4617-8AE0-3309304047DD",
    "exportFormats": [
    ],
    "includedLayerIds": [
    ],
    "layerOptions": 0,
    "shouldTrim": false
  },
  "frame": {
    "_class": "rect",
    "constrainProportions": false,
    "do_objectID": "35980262-90E6-4588-8F48-5025A5D53CFB",
    "height": 24,
    "width": 196,
    "x": 0,
    "y": 0
  },
  "glyphBounds": "{{1, 3}, {194, 19}}",
  "hasClippingMask": false,
  "isFixedToViewport": false,
  "isFlippedHorizontal": false,
  "isFlippedVertical": false,
  "isLocked": false,
  "isVisible": true,
  "layerListExpandedType": 0,
  "lineSpacingBehaviour": 2,
  "name": "Subscriptions",
  "nameIsFixed": false,
  "resizingConstraint": 47,
  "resizingType": 0,
  "rotation": 0,
  "shouldBreakMaskChain": false,
  "style": {
    "_class": "style",
    "do_objectID": "D50A2B74-64D9-46BF-B5A7-1B61A16528DC",
    "endMarkerType": 0,
    "miterLimit": 10,
    "startMarkerType": 0,
    "textStyle": {
      "_class": "textStyle",
      "do_objectID": "984ED04F-8ECF-477E-8F9E-C7E1F7E2DC3D",
      "encodedAttributes": {
        "MSAttributedStringColorAttribute": {
          "_class": "color",
          "alpha": 1,
          "blue": 0,
          "green": 0,
          "red": 0
        },
        "MSAttributedStringFontAttribute": {
          "_class": "fontDescriptor",
          "attributes": {
            "name": "SFProText-Heavy",
            "size": 24
          }
        },
        "MSAttributedStringTextTransformAttribute": 1,
        "kerning": -1,
        "paragraphStyle": {
          "_class": "paragraphStyle",
          "alignment": 0,
          "maximumLineHeight": 24,
          "minimumLineHeight": 24,
          "paragraphSpacing": 4
        },
        "textStyleVerticalAlignmentKey": 0
      },
      "verticalAlignment": 0
    },
    "windingRule": 1
  },
  "textBehaviour": 0
}